{
  "review": [
    {
      "place_id": 1,
      "rate": 4,
      "content": "초밥 구성이 정말 좋아요!",
      "tags": [
        "맛집",
        "가성비",
        "간단한 한 끼"
      ]
    },
    {
      "place_id": 2,
      "rate": 5,
      "content": "음식도 맛있고 분위기도 좋아요",
      "tags": [
        "간단한 한 끼",
        "분위기 좋은"
      ]
    },
    {
      "place_id": 3,
      "rate": 3,
      "content": "음식도 맛있고 분위기도 좋아요",
      "tags": [
        "간단한 한 끼",
        "분위기 좋은"
      ]
    },
    {
      "place_id": 4,
      "rate": 2,
      "content": "음식도 맛있고 분위기도 좋아요",
      "tags": [
        "간단한 한 끼",
        "분위기 좋은"
      ]
    },
    {
      "place_id": 5,
      "rate": 1,
      "content": "음식도 맛있고 분위기도 좋아요",
      "tags": [
        "간단한 한 끼",
        "분위기 좋은"
      ]
    },
    {
      "place_id": 6,
      "rate": 4,
      "content": "초밥 구성이 정말 좋아요!",
      "tags": [
        "맛집",
        "가성비",
        "간단한 한 끼"
      ]
    },
    {
      "place_id": 7,
      "rate": 5,
      "content": "음식도 맛있고 분위기도 좋아요",
      "tags": [
        "간단한 한 끼",
        "분위기 좋은"
      ]
    },
    {
      "place_id": 8,
      "rate": 3,
      "content": "음식도 맛있고 분위기도 좋아요",
      "tags": [
        "간단한 한 끼",
        "분위기 좋은"
      ]
    },
    {
      "place_id": 9,
      "rate": 2,
      "content": "음식도 맛있고 분위기도 좋아요",
      "tags": [
        "간단한 한 끼",
        "분위기 좋은"
      ]
    },
    {
      "place_id": 10,
      "rate": 1,
      "content": "음식도 맛있고 분위기도 좋아요",
      "tags": [
        "간단한 한 끼",
        "분위기 좋은"
      ]
    },
    {
      "place_id": 79,
      "rate": 4,
      "content": "초밥 구성이 정말 좋아요!",
      "tags": [
        "맛집",
        "가성비",
        "간단한 한 끼"
      ]
    },
    {
      "place_id": 80,
      "rate": 5,
      "content": "음식도 맛있고 분위기도 좋아요",
      "tags": [
        "간단한 한 끼",
        "분위기 좋은"
      ]
    },
    {
      "place_id": 81,
      "rate": 3,
      "content": "음식도 맛있고 분위기도 좋아요",
      "tags": [
        "간단한 한 끼",
        "분위기 좋은"
      ]
    },
    {
      "place_id": 82,
      "rate": 2,
      "content": "음식도 맛있고 분위기도 좋아요",
      "tags": [
        "간단한 한 끼",
        "분위기 좋은"
      ]
    },
    {
      "place_id": 83,
      "rate": 1,
      "content": "음식도 맛있고 분위기도 좋아요",
      "tags": [
        "간단한 한 끼",
        "분위기 좋은"
      ]
    },
    {
      "place_id": 84,
      "rate": 4,
      "content": "초밥 구성이 정말 좋아요!",
      "tags": [
        "맛집",
        "가성비",
        "간단한 한 끼"
      ]
    },
    {
      "place_id": 85,
      "rate": 5,
      "content": "음식도 맛있고 분위기도 좋아요",
      "tags": [
        "간단한 한 끼",
        "분위기 좋은"
      ]
    },
    {
      "place_id": 86,
      "rate": 3,
      "content": "음식도 맛있고 분위기도 좋아요",
      "tags": [
        "간단한 한 끼",
        "분위기 좋은"
      ]
    },
    {
      "place_id": 87,
      "rate": 2,
      "content": "음식도 맛있고 분위기도 좋아요",
      "tags": [
        "간단한 한 끼",
        "분위기 좋은"
      ]
    },
    {
      "place_id": 88,
      "rate": 1,
      "content": "음식도 맛있고 분위기도 좋아요",
      "tags": [
        "간단한 한 끼",
        "분위기 좋은"
      ]
    }
  ]
}